odoo/addons/base_ubl_parse/README.rst
odoo/addons/base_ubl_parse/__init__.py
odoo/addons/base_ubl_parse/__manifest__.py
odoo/addons/base_ubl_parse/i18n/base_ubl_parse.pot
odoo/addons/base_ubl_parse/i18n/it.po
odoo/addons/base_ubl_parse/models/__init__.py
odoo/addons/base_ubl_parse/models/ubl.py
odoo/addons/base_ubl_parse/readme/CONTRIBUTORS.md
odoo/addons/base_ubl_parse/readme/CREDITS.md
odoo/addons/base_ubl_parse/readme/DESCRIPTION.md
odoo/addons/base_ubl_parse/static/description/icon.png
odoo/addons/base_ubl_parse/static/description/index.html
odoo/addons/base_ubl_parse/tests/__init__.py
odoo/addons/base_ubl_parse/tests/test_ubl_parse.py
odoo/addons/base_ubl_parse/tests/samples/UBL-Invoice-2.1-Example.xml
odoo/addons/base_ubl_parse/tests/samples/UBL-Order-2.1-Example.xml
odoo_addon_base_ubl_parse-18.0.1.0.0.4.dist-info/METADATA
odoo_addon_base_ubl_parse-18.0.1.0.0.4.dist-info/WHEEL
odoo_addon_base_ubl_parse-18.0.1.0.0.4.dist-info/top_level.txt
odoo_addon_base_ubl_parse-18.0.1.0.0.4.dist-info/RECORD
